MANIFEST.in
setup.py
./LICENSE
./README.md
./__init__.py
./__main__.py
./javaobj.py
sparkpickle.egg-info/PKG-INFO
sparkpickle.egg-info/SOURCES.txt
sparkpickle.egg-info/dependency_links.txt
sparkpickle.egg-info/top_level.txt