Metadata-Version: 1.1
Name: sparkpickle
Version: 1.0.1
Summary: Provides functions for reading SequenceFile-s with Python pickles.
Home-page: https://github.com/src-d/sparkpickle
Author: Vadim Markovtsev
Author-email: vadim@sourced.tech
License: Apache 2.0
Download-URL: https://github.com/src-d/sparkpickle
Keywords: spark,pyspark,hadoop,rdd,pickle
Platform: UNKNOWN
Classifier: Development Status :: 3 - Alpha
Classifier: Environment :: Console
Classifier: Intended Audience :: Developers
Classifier: License :: OSI Approved :: Apache Software License
Classifier: Operating System :: POSIX
Classifier: Programming Language :: Python :: 2.7
Classifier: Programming Language :: Python :: 3.2
Classifier: Programming Language :: Python :: 3.3
Classifier: Programming Language :: Python :: 3.4
Classifier: Topic :: Software Development :: Libraries
